<?xml version="1.0" encoding="UTF-8"?>
<objects serializationModel="Studio.02.02.00">
	<object class="SandboxScene" id="{b0985dd2-3883-44ed-b674-54866580fef7}">
		<property name="name">
			<value>SchoolHallway</value>
		</property>
		<relationship name="folder">
			<destination>{b8d6ab47-216f-41ab-afe9-a8ce19f1d8a4}</destination>
		</relationship>
		<relationship name="markerTracks">
			<destination>{6b132c7b-720f-4cf4-8bec-f60abd161054}</destination>
		</relationship>
		<relationship name="timeline">
			<destination>{1085be16-f3d4-4cd0-917f-0e7ddf79b356}</destination>
		</relationship>
		<relationship name="emitters">
			<destination>{08c1eb98-e1fe-4c3b-a727-71f21d211aaa}</destination>
			<destination>{c7e5c29b-b3a4-4e41-80ec-c5211f16a274}</destination>
		</relationship>
	</object>
	<object class="MarkerTrack" id="{6b132c7b-720f-4cf4-8bec-f60abd161054}" />
	<object class="Timeline" id="{1085be16-f3d4-4cd0-917f-0e7ddf79b356}" />
	<object class="SandboxEmitter" id="{08c1eb98-e1fe-4c3b-a727-71f21d211aaa}">
		<property name="positionX">
			<value>-0.300000012</value>
		</property>
		<property name="positionZ">
			<value>0.974999785</value>
		</property>
		<property name="rotationY">
			<value>44.1603699</value>
		</property>
		<relationship name="event">
			<destination>{07606e34-575b-488c-abb9-b324e6367f82}</destination>
		</relationship>
	</object>
	<object class="SandboxEmitter" id="{c7e5c29b-b3a4-4e41-80ec-c5211f16a274}">
		<property name="positionX">
			<value>0.099999994</value>
		</property>
		<property name="positionZ">
			<value>-0.650000036</value>
		</property>
		<property name="rotationY">
			<value>-87.1090927</value>
		</property>
		<relationship name="event">
			<destination>{f5d635a3-90a9-4439-b0dd-c9b11f648ee8}</destination>
		</relationship>
	</object>
</objects>
